gstbasetransform.py
gstbasetransform-0.1.0.dist-info/DESCRIPTION.rst
gstbasetransform-0.1.0.dist-info/LICENSE.txt
gstbasetransform-0.1.0.dist-info/METADATA
gstbasetransform-0.1.0.dist-info/RECORD
gstbasetransform-0.1.0.dist-info/WHEEL
gstbasetransform-0.1.0.dist-info/metadata.json
gstbasetransform-0.1.0.dist-info/top_level.txt
