Metadata-Version: 2.0
Name: gstbasetransform
Version: 0.1.0
Summary: A module that makes GstBase.BaseTransform python-compatible
Home-page: https://github.com/Muges/gstbasetransform
Author: Muges
Author-email: git@muges.fr
License: LGPL
Platform: UNKNOWN
Classifier: License :: OSI Approved :: GNU Lesser General Public License v2 (LGPLv2)
Classifier: Programming Language :: Python
Classifier: Programming Language :: Python :: 2
Classifier: Programming Language :: Python :: 2.7
Classifier: Programming Language :: Python :: 3
Classifier: Programming Language :: Python :: 3.4
Classifier: Programming Language :: Python :: 3.5
Classifier: Programming Language :: Python :: 3.6
Classifier: Topic :: Multimedia :: Sound/Audio
Requires-Dist: six
